{"title":"Combined feed","url":"https://TicketOpen.github.io/naver/all.xml","elements":[{"title":"후원\n\t\t\t\t\t\t\t\t\t\t\t오페라 <탄호이저> (네이버 공연 live beta)","contents":"10월 19일(토) 15:00","link":"https://patron.naver.com/ntv/c/intro/koreanationalopera","retrieved":1727065154469,"image":"https://phinf.pstatic.net/tvcast/20240910_122/m6ojv_1725955090849n6StO_JPEG/1725955090716.jpg"},{"title":"후원\n\t\t\t\t\t\t\t\t\t\t\t뮤지컬 <안나, 차이코프스키> 1차 중계 (네이버 공연 live beta)","contents":"10월 21일(월) 20:00","link":"https://patron.naver.com/ntv/c/intro/orchard","retrieved":1728528523339,"image":"https://phinf.pstatic.net/tvcast/20241004_139/lLNaW_1728026655819S3wX2_JPEG/1728026655726.jpg"},{"title":"후원\n\t\t\t\t\t\t\t\t\t\t\t뮤지컬 <안나, 차이코프스키> 2차 중계 (네이버 공연 live beta)","contents":"10월 28일(월) 20:00","link":"https://patron.naver.com/ntv/c/intro/orchard","retrieved":1728528523339,"image":"https://phinf.pstatic.net/tvcast/20241004_243/8KpAc_1728030805485Xfkfe_JPEG/1728030805458.jpg"},{"title":"후원\n\t\t\t\t\t\t\t\t\t\t\t뮤지컬 <안나, 차이코프스키> 3차 중계 (네이버 공연 live beta)","contents":"11월 04일(월) 20:00","link":"https://patron.naver.com/ntv/c/intro/orchard","retrieved":1728528523339,"image":"https://phinf.pstatic.net/tvcast/20241004_249/x2HFz_1728030995994espjR_JPEG/1728030995970.jpg"},{"title":"오페라  <탄호이저> ❝ 뜨겁게 기도하고 있는 저기 저사람은 누구인가? ❞ (네이버 공연 live beta ─ 하이라이트)","contents":"후원","link":"https://patron.naver.com/ntv/c/intro/koreanationalopera","retrieved":1727065154469,"image":"https://g-grafolio.pstatic.net/20240923_277/1727064351530wgHY1_PNG/8j4cgqtr.png"},{"title":"뮤지컬 <안나, 차이코프스키> (네이버 공연 live beta ─ 하이라이트)","contents":"후원","link":"https://patron.naver.com/ntv/c/intro/orchard","retrieved":1728528523339,"image":"https://g-grafolio.pstatic.net/20241010_273/1728528886303nacq4_JPEG/5.JPG"},{"title":"오페라  <탄호이저> ❝ 뜨겁게 기도하고 있는 저기 저사람은 누구인가? ❞ (네이버 공연 live beta ─ 하이라이트)","contents":"후원","link":"https://patron.naver.com/ntv/c/intro/koreanationalopera","retrieved":1727065154469,"image":"https://g-grafolio.pstatic.net/20240923_277/1727064351530wgHY1_PNG/8j4cgqtr.png"},{"title":"뮤지컬 <안나, 차이코프스키> (네이버 공연 live beta ─ 하이라이트)","contents":"후원","link":"https://patron.naver.com/ntv/c/intro/orchard","retrieved":1728528523339,"image":"https://g-grafolio.pstatic.net/20241010_273/1728528886303nacq4_JPEG/5.JPG"}]}