{"title":"네이버 공연 live beta","url":"https://live.naver.com/","favicon":"https://live.naver.com/favicon.ico","elements":[{"title":"쇼핑\n\t\t\t\t\t\t\t\t\t\t\t프랑스 국립자연사박물관 특별전","contents":"12월 09일(목) 20:00","link":"https://shoppinglive.naver.com/livebridge/337128","retrieved":1638692231311,"image":"https://g-grafolio.pstatic.net/20211201_151/1638342034129JC2dJ_PNG/246x138.png"},{"title":"2021 서울국제공연예술제(SPAF) <디스토피아> 녹화중계","contents":"12월 09일(목) 20:00","link":"https://blog.naver.com/jump_arko/222559489102","retrieved":1638706958657,"image":"https://phinf.pstatic.net/tvcast/20211104_148/tr9C9_1636006012581nDxgz_PNG/1636006012560.png"},{"title":"쇼핑\n\t\t\t\t\t\t\t\t\t\t\t<동행, 다시 함께> 2021 DIMF 뮤지컬스타 콘서트","contents":"12월 12일(일) 17:00","link":"https://shoppinglive.naver.com/livebridge/338023","retrieved":1639048375203,"image":"https://g-grafolio.pstatic.net/20211209_64/1639046211191lGGel_JPEG/364x180.jpg"},{"title":"<동행, 다시 함께> 2021 DIMF 뮤지컬스타 콘서트","contents":"12월 12일(일) 17:00","link":"https://blog.naver.com/dimfmusical/222585812044","retrieved":1639048375204,"image":"https://phinf.pstatic.net/tvcast/20211209_36/xb7fq_1639038396592LjKtc_JPEG/1639038396574.jpg"},{"title":"쇼핑\n\t\t\t\t\t\t\t\t\t\t\t<동행, 다시 함께> DIMF The Concert","contents":"12월 13일(월) 19:30","link":"https://shoppinglive.naver.com/livebridge/338051","retrieved":1639048375204,"image":"https://g-grafolio.pstatic.net/20211209_48/1639046424654jQjbg_JPEG/246X138.jpg"},{"title":"<동행, 다시 함께> DIMF The Concert","contents":"12월 13일(월) 19:30","link":"https://blog.naver.com/dimfmusical/222585818125","retrieved":1639048375205,"image":"https://phinf.pstatic.net/tvcast/20211209_103/3l4Yf_163903881893445ohD_JPEG/1639038818891.jpg"},{"title":"2021 서울국제음악제 '연결,만남'","contents":"12월 13일(월) 19:30","link":"https://tv.naver.com/l/93868","retrieved":1639017585471,"image":"https://phinf.pstatic.net/tvcast/20211208_92/SNXcd_1638927316404uo3Hs_JPEG/1638927316317.jpg"},{"title":"후원\n\t\t\t\t\t\t\t\t\t\t\t창작 뮤지컬 <루드윅:베토벤 더 피아노>","contents":"12월 13일(월) 20:00","link":"https://patron.naver.com/ntv/c/intro/orchard","retrieved":1638803778171,"image":"https://phinf.pstatic.net/tvcast/20211129_177/0mZ1Z_1638173044005y3PN7_JPEG/1638173043948.jpg"},{"title":"2021 서울국제음악제 실내악 시리즈 2 '시냇물'","contents":"12월 14일(화) 19:30","link":"https://tv.naver.com/l/93870","retrieved":1639017585473,"image":"https://phinf.pstatic.net/tvcast/20211208_111/dZlFb_16389295597547hPJB_JPEG/1638929559678.jpg"},{"title":"연극 <줄리엣과 줄리엣> 녹화중계","contents":"12월 14일(화) 20:00","link":"https://blog.naver.com/jump_arko/222529432243","retrieved":1638879932279,"image":"https://phinf.pstatic.net/tvcast/20211102_194/wso8G_1635836067709VKaqO_PNG/1635836067658.png"}]}